{
  "parent": "minecraft:recipes/root",
  "rewards": {
    "recipes": [
      "resourcemelons:emerald_melon"
    ]
  },
  "criteria": {
    "has_emerald_melon_slice": {
      "trigger": "minecraft:inventory_changed",
      "conditions": {
        "items": [
          {
            "items": [
              "resourcemelons:emerald_melon_slice"
            ]
          }
        ]
      }
    },
    "has_the_recipe": {
      "trigger": "minecraft:recipe_unlocked",
      "conditions": {
        "recipe": "resourcemelons:emerald_melon"
      }
    }
  },
  "requirements": [
    [
      "has_emerald_melon_slice",
      "has_the_recipe"
    ]
  ]
}